setup.py
src/pyfunctor/__init__.py
src/pyfunctor/functor.py
src/pyfunctor/list.py
src/pyfunctor/maybe.py
src/pyfunctor.egg-info/PKG-INFO
src/pyfunctor.egg-info/SOURCES.txt
src/pyfunctor.egg-info/dependency_links.txt
src/pyfunctor.egg-info/top_level.txt