Metadata-Version: 1.1
Name: pyfunctor
Version: 0.1.3
Summary: A Functor library for Python
Home-page: https://github.com/jnamika/pyfunctor
Author: Jun Namikawa
Author-email: jnamika@gmail.com
License: ISC License (ISCL)
Keywords: functor lazy pipeline block
Platform: UNKNOWN
Classifier: Development Status :: 3 - Alpha
Classifier: Intended Audience :: Developers
Classifier: License :: OSI Approved :: ISC License (ISCL)
Classifier: Operating System :: OS Independent
Classifier: Programming Language :: Python
Classifier: Programming Language :: Python :: 2
Classifier: Programming Language :: Python :: 2.7
Classifier: Programming Language :: Python :: 3
Classifier: Programming Language :: Python :: 3.2
Classifier: Programming Language :: Python :: 3.3
Classifier: Topic :: Software Development :: Libraries :: Python Modules
